setup.py
base64image/__init__.py
base64image/base64image.py
base64image.egg-info/PKG-INFO
base64image.egg-info/SOURCES.txt
base64image.egg-info/dependency_links.txt
base64image.egg-info/requires.txt
base64image.egg-info/top_level.txt